seliky/__init__.py
seliky/__lock__.py
seliky/conftest.py
seliky/logger.py
seliky/seliky.py
seliky-23.12.dist-info/LICENSE
seliky-23.12.dist-info/METADATA
seliky-23.12.dist-info/WHEEL
seliky-23.12.dist-info/top_level.txt
seliky-23.12.dist-info/RECORD
