Metadata-Version: 2.1
Name: seliky
Version: 23.12
Summary: a better ui autotest lib based on selenium, compatible with robot framework
Home-page: https://gitee.com/teark/seliky.git
Author: TEARK
Author-email: 913355434@qq.com
Classifier: Programming Language :: Python :: 3
Classifier: License :: OSI Approved :: MIT License
Classifier: Operating System :: OS Independent
Requires-Python: >=3.6
License-File: LICENSE
Requires-Dist: selenium >=3.5.0
